assets/logo.ico
smd/__init__.py
smd/__main__.py
smd/downloader.py
social_media_downloader-1.1.12.dist-info/licenses/LICENSE
social_media_downloader-1.1.12.dist-info/METADATA
social_media_downloader-1.1.12.dist-info/WHEEL
social_media_downloader-1.1.12.dist-info/entry_points.txt
social_media_downloader-1.1.12.dist-info/top_level.txt
social_media_downloader-1.1.12.dist-info/RECORD
