Metadata-Version: 2.4
Name: social-media-downloader
Version: 1.1.12
Summary: A command-line tool to download videos from various social media platforms like YouTube, TikTok, Facebook, Instagram, X & more. It supports instagram batch downloads, format selection, and maintains a download history.
Author-email: nayandas69 <nayanchandradas@hotmail.com>
License: MIT
Project-URL: Source Code, https://github.com/nayandas69/Social-Media-Downloader
Project-URL: Bug Tracker, https://github.com/nayandas69/Social-Media-Downloader/issues
Project-URL: Documentation, https://github.com/nayandas69/Social-Media-Downloader#readme
Project-URL: Homepage, https://smd-toolkit.vercel.app
Keywords: smd,cli tool,video downloader,tiktok downloader,youtube downloader,facebook downloader,instagram downloader,social media downloader
Classifier: Development Status :: 5 - Production/Stable
Classifier: Environment :: Console
Classifier: Intended Audience :: Developers
Classifier: Intended Audience :: End Users/Desktop
Classifier: License :: OSI Approved :: MIT License
Classifier: Operating System :: OS Independent
Classifier: Programming Language :: Python :: 3.10
Classifier: Programming Language :: Python :: 3.11
Classifier: Programming Language :: Python :: 3.12
Classifier: Topic :: Internet
Classifier: Topic :: Multimedia :: Video
Classifier: Topic :: Software Development :: Libraries
Classifier: Topic :: Utilities
Requires-Python: >=3.10
License-File: LICENSE
Requires-Dist: yt-dlp>=2024.1.0
Requires-Dist: instaloader>=4.11.0
Requires-Dist: tqdm>=4.66.0
Requires-Dist: requests>=2.32.0
Requires-Dist: ffmpeg-python>=0.2.0
Requires-Dist: certifi>=2024.2.0
Requires-Dist: setuptools>=69.0.0
Requires-Dist: wheel>=0.42.0
Requires-Dist: pyfiglet>=1.0.0
Requires-Dist: termcolor>=2.4.0
Requires-Dist: tabulate>=0.9.0
Provides-Extra: dev
Requires-Dist: pytest>=8.0.0; extra == "dev"
Requires-Dist: pytest-cov>=4.0.0; extra == "dev"
Requires-Dist: flake8>=7.0.0; extra == "dev"
Requires-Dist: black>=24.0.0; extra == "dev"
Requires-Dist: mypy>=1.8.0; extra == "dev"
Requires-Dist: isort>=5.13.0; extra == "dev"
Requires-Dist: pre-commit>=3.6.0; extra == "dev"
Dynamic: license-file
